{
  "status": {
    "statusCode": 200,
    "statusText": "ALIVE",
    "apiVersion": "0.1.0"
  },
  "users": {
    "dungntnew": {
      "id": 12121,
      "displayName": "Nguyen Tri Dung"
    },
    "nghiemdaovan": {
      "id": 1111,
      "displayName": "Dao Van Nghiem"
    }
  },
  "blogs": {
    "total": 250,
    "current": 99,
    "blogItems": {
      "blog-1": {
        "title": "blog title -1",
        "url": "/blogs/blog-1",
        "lastUpdate": "20170101 10:30",
        "coverImageUrl": "/img/event-1.jpg",
        "tags": ["肉", "そば"],
        "content": "説明が入ります。説明が入ります。説明が入ります。説明が入ります。説明が入ります"
      },
      "blog-2": {
        "title": "blog title -2",
        "url": "/blogs/blog-2",
        "lastUpdate": "20170101 11:30",
        "coverImageUrl": "/img/event-2.jpg",
        "tags": ["肉", "そば"],
        "content": "説明が入ります。説明が入ります。説明が入ります。説明が入ります。説明が入ります"
      },
      "blog-3": {
        "title": "blog title -3",
        "url": "/blogs/blog-3",
        "lastUpdate": "20170102 12:30",
        "coverImageUrl": "/img/event-3.jpg",
        "tags": ["肉", "そば"],
        "content": "説明が入ります。説明が入ります。説明が入ります。説明が入ります。説明が入ります"
      },
      "blog-4": {
        "title": "blog title -4",
        "url": "/blogs/blog-4",
        "lastUpdate": "20170103 09:30",
        "coverImageUrl": "/img/event-4.jpg",
        "tags": ["肉", "そば"],
        "content": "説明が入ります。説明が入ります。説明が入ります。説明が入ります。説明が入ります"
      }
    }
  },

  "blogdetails": [
    {
      "id": "blog-1",
      "title": "event-1",
      "url": "/blogs/blog-1",
      "lastUpdate": "20170101 10:30",
      "tags": ["肉", "そば"],
      "content": "説明が入ります。説明が入ります。説明が入ります。説明が入ります。説明が入ります",
      "coverImageUrl": "/img/event-4.jpg"
  }
  ],
  "get_todos": [
    {
      "id": 1,
      "text": "KAKAKAK"
    },
    {
      "id": 2,
      "text": "CCC"
    },
    {
      "id": 3,
      "text": "AA"
    },
    {
      "id": 4,
      "text": "GGG"
    }
  ],
  "post_todos": [
    {
      "id": 1,
      "text": "KAKAKAK"
    },
    {
      "id": 2,
      "text": "HIHIHI"
    },
    {
      "text": "HIHIHI",
      "id": 3
    },
    {
      "text": "HIHIHI",
      "id": 4
    },
    {
      "text": "HIHIHI",
      "id": 5
    },
    {
      "text": "HIHIHI",
      "id": 6
    },
    {
      "text": "HIHIHI",
      "id": 7
    },
    {
      "text": "HIHIHI",
      "id": 8
    },
    {
      "text": "HIHIHI",
      "id": 9
    },
    {
      "text": "HIHIHI",
      "id": 10
    },
    {
      "text": "HIHIHI",
      "id": 11
    },
    {
      "text": "HIHIHI",
      "id": 12
    },
    {
      "text": "HIHIHI",
      "id": 13
    },
    {
      "text": "HIHIHI",
      "id": 14
    },
    {
      "text": "HIHIHI",
      "id": 15
    },
    {
      "text": "HIHIHI",
      "id": 16
    },
    {
      "text": "HIHIHI",
      "id": 17
    },
    {
      "text": "HIHIHI",
      "id": 18
    },
    {
      "text": "HIHIHI",
      "id": 19
    },
    {
      "text": "HIHIHI",
      "id": 20
    },
    {
      "text": "HIHIHI",
      "id": 21
    },
    {
      "text": "HIHIHI",
      "id": 22
    },
    {
      "text": "HIHIHI",
      "id": 23
    },
    {
      "text": "HIHIHI",
      "id": 24
    },
    {
      "text": "HIHIHI",
      "id": 25
    },
    {
      "text": "HIHIHI",
      "id": 26
    },
    {
      "text": "HIHIHI",
      "id": 27
    },
    {
      "text": "HIHIHI",
      "id": 28
    },
    {
      "text": "HIHIHI",
      "id": 29
    },
    {
      "text": "HIHIHI",
      "id": 30
    },
    {
      "text": "HIHIHI",
      "id": 31
    },
    {
      "text": "HIHIHI",
      "id": 32
    },
    {
      "text": "HIHIHI",
      "id": 33
    },
    {
      "text": "HIHIHI",
      "id": 34
    },
    {
      "text": "HIHIHI",
      "id": 35
    },
    {
      "text": "HIHIHI",
      "id": 36
    },
    {
      "text": "HIHIHI",
      "id": 37
    },
    {
      "text": "HIHIHI",
      "id": 38
    },
    {
      "text": "HIHIHI",
      "id": 39
    },
    {
      "text": "HIHIHI",
      "id": 40
    },
    {
      "text": "HIHIHI",
      "id": 41
    },
    {
      "text": "HIHIHI",
      "id": 42
    },
    {
      "text": "HIHIHI",
      "id": 43
    },
    {
      "text": "HIHIHI",
      "id": 44
    },
    {
      "text": "HIHIHI",
      "id": 45
    },
    {
      "text": "HIHIHI",
      "id": 46
    },
    {
      "text": "HIHIHI",
      "id": 47
    },
    {
      "text": "HIHIHI",
      "id": 48
    },
    {
      "text": "HIHIHI",
      "id": 49
    },
    {
      "text": "HIHIHI",
      "id": 50
    },
    {
      "text": "HIHIHI",
      "id": 51
    },
    {
      "text": "HIHIHI",
      "id": 52
    },
    {
      "text": "HIHIHI",
      "id": 53
    },
    {
      "text": "HIHIHI",
      "id": 54
    },
    {
      "text": "HIHIHI",
      "id": 55
    },
    {
      "text": "HIHIHI",
      "id": 56
    },
    {
      "text": "HIHIHI",
      "id": 57
    },
    {
      "text": "HIHIHI",
      "id": 58
    },
    {
      "text": "HIHIHI",
      "id": 59
    },
    {
      "text": "HIHIHI",
      "id": 60
    },
    {
      "text": "HIHIHI",
      "id": 61
    },
    {
      "text": "HIHIHI",
      "id": 62
    },
    {
      "text": "HIHIHI",
      "id": 63
    },
    {
      "text": "HIHIHI",
      "id": 64
    },
    {
      "text": "HIHIHI",
      "id": 65
    },
    {
      "text": "HIHIHI",
      "id": 66
    },
    {
      "text": "HIHIHI",
      "id": 67
    },
    {
      "text": "HIHIHI",
      "id": 68
    },
    {
      "text": "HIHIHI",
      "id": 69
    },
    {
      "text": "HIHIHI",
      "id": 70
    },
    {
      "text": "HIHIHI",
      "id": 71
    },
    {
      "text": "HIHIHI",
      "id": 72
    },
    {
      "text": "HIHIHI",
      "id": 73
    },
    {
      "text": "HIHIHI",
      "id": 74
    },
    {
      "text": "HIHIHI",
      "id": 75
    },
    {
      "text": "HIHIHI",
      "id": 76
    }
  ],
  "events": {
    "total": 100,
    "events": {
      "event-1": {
        "title": "event-1",
        "price": 431,
        "address": "Yokohama 123",
        "tags": [
          "Niku",
          "Tabehodai",
          "Dinner"
        ],
        "target": "Niku",
        "targetName": "Niku niku",
        "joinerCount": 15,
        "joinerLimit": 20,
        "joinerIds": [
          "user-1",
          "user-2",
          "user-3"
        ],
        "openDate": "20160112",
        "registrationDateStart": "20160102",
        "registrationDateEnd": "20160102",
        "url": "/events/event-1",
        "coverImageUrl": "/img/event-1.jpg",
        "eventImageUrls": [
          "img/event/event1-1.png",
          "img/event/event1-2.png"
        ],
        "ownerId": "user-1",
        "ownerUserName": "user-1",
        "ownerFullName": "User-1",
        "ownerAvatarUrl": "https://placeholdit.imgix.net/~text?txtsize=10&txt=100%C3%97100&w=100&h=100"
      },
      "event-2": {
        "title": "event-2",
        "price": 312,
        "address": "Tokyo 123",
        "tags": [
          "Tabehodai",
          "Dinner"
        ],
        "target": "Onokomiyaki",
        "targetName": "Onokomiyaki",
        "joinerCount": 15,
        "joinerLimit": 20,
        "joinerIds": [
          "user-1",
          "user-2",
          "user-3"
        ],
        "openDate": "20160112",
        "registrationDateStart": "20160102",
        "registrationDateEnd": "20160102",
        "url": "/events/event-2",
        "coverImageUrl": "/img/event-2.jpg",
        "eventImageUrls": [
          "img/event/event2-1.png",
          "img/event/event2-2.png"
        ],
        "ownerId": "user-2",
        "ownerUserName": "user-2",
        "ownerFullName": "User-2",
        "ownerAvatarUrl": "https://placeholdit.imgix.net/~text?txtsize=10&txt=100%C3%97100&w=100&h=100"
      },
      "event-3": {
        "title": "event-3",
        "price": 34444,
        "address": "Tamachi 123",
        "tags": [
          "Niku",
          "Tabehodai",
          "Dinner"
        ],
        "target": "Niku",
        "targetName": "Niku niku",
        "joinerCount": 15,
        "joinerLimit": 20,
        "joinerIds": [
          "user-1",
          "user-2",
          "user-3"
        ],
        "openDate": "20160112",
        "registrationDateStart": "20160102",
        "registrationDateEnd": "20160102",
        "url": "/events/event-3",
        "coverImageUrl": "/img/event-3.jpg",
        "eventImageUrls": [
          "img/event/event3-1.png",
          "img/event/event3-2.png"
        ],
        "ownerId": "user-3",
        "ownerUserName": "user-3",
        "ownerFullName": "User-3",
        "ownerAvatarUrl": "https://placeholdit.imgix.net/~text?txtsize=10&txt=100%C3%97100&w=100&h=100"
      }
    }
  },
  "details": [
    {
      "id": "event-1",
      "title": "event-1",
      "price": 431,
      "zipCode": "105-0014",
      "address1": "東京都",
      "address2": "港区",
      "address3": "芝2-26-6",
      "tags": [
        "Niku",
        "Tabehodai",
        "Dinner"
      ],
      "instarHashTag": "春結婚式",
      "dressCode": "正装フォーマル",
      "placeType": "結婚式場",
      "supplements": [
        "テーブル椅子",
        "駐車場",
        "WiFi"
      ],
      "target": "Niku",
      "targetName": "Niku niku",
      "genre": "肉",
      "genreName": "肉肉肉",
      "memberCount": 15,
      "joinerLimit": 20,
      "joined": false,
      "liked": false,
      "members": [
        {
          "id": "user-1",
          "url": "/members/user-1",
          "userAvatar": "/img/avatar.png",
          "displayName": "Name 1"
        },
        {
          "id": "user-2",
          "url": "/members/user-2",
          "userAvatar": "/img/avatar.png",
          "displayName": "Name 2"
        },
        {
          "id": "user-3",
          "url": "/members/user-3",
          "userAvatar": "/img/avatar.png",
          "displayName": "Name 3"
        },
        {
          "id": "user-4",
          "url": "/members/user-4",
          "userAvatar": "/img/avatar.png",
          "displayName": "Name 4"
        }
      ],
      "eventImageUrls": [
        "/img/event-1.jpg",
        "/img/event-2.jpg",
        "/img/event-3.jpg",
        "/img/event-1.jpg",
        "/img/event-2.jpg",
        "/img/event-3.jpg",
        "/img/event-1.jpg",
        "/img/event-2.jpg",
        "/img/event-3.jpg",
        "/img/event-1.jpg",
        "/img/event-2.jpg",
        "/img/event-3.jpg",
        "/img/event-1.jpg",
        "/img/event-2.jpg",
        "/img/event-3.jpg"
      ],
      "coverImageUrl": "/img/event-1.jpg",
      "openDate": "20160112",
      "closeDate": "20160112",
      "registrationDateStart": "20160102",
      "registrationDateEnd": "20160102",
      "url": "/events/event-1",
      "owner": {
        "id": "user-1",
        "avatarUrl": "/img/avatar.png",
        "displayName": "Kirito 2",
        "url": "/member/kirito2",
        "rank": 2,
        "createdEventCount": 11
      },
      "description": "スペインを中心に海外で9年間修行し、東京のガストロノミーの最高峰のひとつ「日本料理 龍吟」と世界的に有名なスペイン料理の「レストラン サンパウ」東京店のスーシェフを勤めた本多シェフが、2011年4月に麻布十番にオープンしたスペイン料理レストラン。"
    }
  ]
}
